spinsfast-2022.4.10.dist-info/RECORD
spinsfast-2022.4.10.dist-info/LICENSE
spinsfast-2022.4.10.dist-info/WHEEL
spinsfast-2022.4.10.dist-info/COPYING
spinsfast-2022.4.10.dist-info/top_level.txt
spinsfast-2022.4.10.dist-info/METADATA
spinsfast/__init__.py
spinsfast/cextension.cpython-312-darwin.so
spinsfast/.dylibs/libfftw3.3.dylib
