Metadata-Version: 2.1
Name: spinsfast
Version: 2022.4.10
Summary: Fast and exact spin-s spherical-harmonic transforms
Home-page: https://github.com/moble/spinsfast
Maintainer: Mike Boyle
Maintainer-email: mob22@cornell.edu
License-File: LICENSE
License-File: COPYING
